inline_admin_extensions/__init__.py
inline_admin_extensions/admin.py
inline_admin_extensions/templates/admin3/edit_inline/tabular.html
inline_admin_extensions/templates/admin3/edit_inline/tabular_header_row.html
inline_admin_extensions/templates/admin3/edit_inline/tabular_inline_pagination.html
inline_admin_extensions/templates/admin3/edit_inline/tabular_paginated.html
inline_admin_extensions/templatetags/__init__.py
inline_admin_extensions/templatetags/inline_admin_paginator.py
Django_inline_column_extension-1.0.dist-info/LICENSE
Django_inline_column_extension-1.0.dist-info/METADATA
Django_inline_column_extension-1.0.dist-info/WHEEL
Django_inline_column_extension-1.0.dist-info/top_level.txt
Django_inline_column_extension-1.0.dist-info/RECORD
