Metadata-Version: 2.1
Name: Django-inline-column-extension
Version: 1.0
Summary: With this package you can paginate and sort inline admin
Author-email: navid shaghouzaei <navid.shagho003@gmail.com>
Project-URL: Homepage, https://github.com/shagho/Django-inline-column-extension
Project-URL: Issues, https://github.com/shagho/Django-inline-column-extension/issues
Classifier: Programming Language :: Python :: 3
Classifier: License :: OSI Approved :: MIT License
Classifier: Operating System :: OS Independent
Requires-Python: >=3.8
License-File: LICENSE
Requires-Dist: django >=2.2
